{
    "calendar": [
        {"month": "sierpień"},
        {"month": "wrzesień",
        "data": [
        {
            "day": 26,
            "classes": ["text-grey", "day-of-month-numeric__item"],
            "content": [{ "text": "","powiat": "", "hour": ""}]
        }, {
            "day": 27,
            "classes": ["text-grey", "day-of-month-numeric__item"],
            "content": [{ "text": "","powiat": "", "hour": ""}]
        }, {
            "day": 28,
            "classes": ["text-grey", "day-of-month-numeric__item"],
            "content": [{ "text": "","powiat": "", "hour": ""}]
        }, {
            "day": 29,
            "classes": ["text-grey", "day-of-month-numeric__item"],
            "content": [{ "text": "","powiat": "", "hour": ""}]
        }, {
            "day": 30,
            "classes": ["text-grey", "day-of-month-numeric__item"],
            "content": [{ "text": "","powiat": "", "hour": ""}]
        }, {
            "day": 31,
            "classes": ["text-grey", "day-of-month-numeric__item"],
            "content": [{ "text": "","powiat": "", "hour": ""}]
        }, {
            "day": 1,
            "dayOfWeek": "niedziela",
            "classes": ["day-of-month-numeric__item", "event-listener"],
            "content": [{ "text": "","powiat": "", "hour": ""}]
        }, {
            "day": 2,
            "dayOfWeek": "poniedziałek",
            "classes": ["day-of-month-numeric__item", "event-listener"],
            "content": [{ "text": "","powiat": "", "hour": ""}]
        }, {
            "day": 3,
            "dayOfWeek": "wtorek",
            "classes": ["day-of-month-numeric__item", "event-listener"],
            "content": [{ "text": "","powiat": "", "hour": ""}]
        }, {
            "day": 4,
            "dayOfWeek": "środa",
            "classes": ["day-of-month-numeric__item", "event-listener"],
            "content": [{ "text": "","powiat": "", "hour": ""}]
        }, {
            "day": 5,
            "dayOfWeek": "czwartek",
            "classes": ["day-of-month-numeric__item", "event-listener"],
            "content": [{ "text": "","powiat": "", "hour": ""}]
        }, {
            "day": 6,
            "dayOfWeek": "piątek",
            "classes": ["day-of-month-numeric__item", "event-listener"],
            "content": [{ "text": "","powiat": "", "hour": ""}]
        }, {
            "day": 7,
            "dayOfWeek": "sobota",
            "classes": ["day-of-month-numeric__item", "event-listener"],
            "content": [{ "text": "","powiat": "", "hour": ""}]
        }, {
            "day": 8,
            "dayOfWeek": "niedziela",
            "classes": ["day-of-month-numeric__item", "event-listener"],
            "content": [{ "text": "","powiat": "", "hour": ""}]
        }, {
            "day": 9,
            "dayOfWeek": "poniedziałek",
            "classes": ["day-of-month-numeric__item", "event-listener"],
            "content": [{ "text": "","powiat": "", "hour": ""}]
        }, {
            "day": 10,
            "dayOfWeek": "wtorek",
            "classes": ["day-of-month-numeric__item", "event-listener"],
            "content": [{ "text": "","powiat": "", "hour": ""}]
        }, {
            "day": 11,
            "dayOfWeek": "środa",
            "classes": ["day-of-month-numeric__item", "event-listener"],
            "content": [{ "text": "","powiat": "", "hour": ""}]
        }, {
            "day": 12,
            "dayOfWeek": "czwartek",
            "classes": ["day-of-month-numeric__item", "event-listener"],
            "content": [{ "text": "","powiat": "", "hour": ""}]
        }, {
            "day": 13,
            "dayOfWeek": "piątek",
            "classes": ["day-of-month-numeric__item", "event-listener"],
            "content": [{ "text": "","powiat": "", "hour": ""}]
        }, {
            "day": 14,
            "dayOfWeek": "sobota",
            "classes": ["day-of-month-numeric__item", "event-listener"],
            "content": [{ "text": "","powiat": "", "hour": ""}]
        }, {
            "day": 15,
            "dayOfWeek": "niedziela",
            "classes": ["day-of-month-numeric__item", "event-listener"],
            "content": [{ "text": "","powiat": "", "hour": ""}]
        }, {
            "day": 16,
            "dayOfWeek": "poniedziałek",
            "classes": ["day-of-month-numeric__item", "event-listener"],
            "content": [{ "text": "","powiat": "", "hour": ""}]
        }, {
            "day": 17,
            "dayOfWeek": "wtorek",
            "classes": ["day-of-month-numeric__item", "event-listener"],
            "content": [{ "text": "","powiat": "", "hour": ""}]
        }, {
            "day": 18,
            "dayOfWeek": "środa",
            "classes": ["day-of-month-numeric__item", "event-listener"],
            "content": [{ "text": "","powiat": "", "hour": ""}]
        }, {
            "day": 19,
            "dayOfWeek": "czwartek",
            "classes": ["day-of-month-numeric__item", "event-listener"],
            "content": [{ "text": "","powiat": "", "hour": ""}]
        }, {
            "day": 20,
            "dayOfWeek": "piątek",
            "classes": ["day-of-month-numeric__item", "event-listener"],
            "content": [{ "text": "","powiat": "", "hour": ""}]
        }, {
            "day": 21,
            "dayOfWeek": "sobota",
            "classes": ["day-of-month-numeric__item", "event-listener"],
            "content": [{ "text": "VI Spotkanie Zespołów Śpiewaczych i Muzycznych \"A mnie jest szkoda lata...\", Chata biesiadna w Kamieńcu","powiat": "powiat_grodziski_calendar", "hour": "15:00"}]
        }, {
            "day": 22,
            "dayOfWeek": "niedziela",
            "classes": ["day-of-month-numeric__item", "event-listener"],
            "content": [{ "text": "","powiat": "", "hour": ""}]
        }, {
            "day": 23,
            "dayOfWeek": "poniedziałek",
            "classes": ["day-of-month-numeric__item", "event-listener"],
            "content": [{ "text": "","powiat": "", "hour": ""}]
        }, {
            "day": 24,
            "dayOfWeek": "wtorek",
            "classes": ["day-of-month-numeric__item", "event-listener"],
            "content": [{ "text": "","powiat": "", "hour": ""}]
        }, {
            "day": 25,
            "dayOfWeek": "środa",
            "classes": ["day-of-month-numeric__item", "event-listener"],
            "content": [{ "text": "","powiat": "", "hour": ""}]
        }, {
            "day": 26,
            "dayOfWeek": "czwartek",
            "classes": ["day-of-month-numeric__item", "event-listener"],
            "content": [{ "text": "","powiat": "", "hour": ""}]
        }, {
            "day": 27,
            "dayOfWeek": "piątek",
            "classes": ["day-of-month-numeric__item", "event-listener"],
            "content": [{ "text": "","powiat": "", "hour": ""}]
        }, {
            "day": 28,
            "dayOfWeek": "sobota",
            "classes": ["day-of-month-numeric__item", "event-listener"],
            "content": [{ "text": "","powiat": "", "hour": ""}]
        }, {
            "day": 29,
            "dayOfWeek": "niedziela",
            "classes": ["day-of-month-numeric__item", "event-listener"],
            "content": [{ "text": "","powiat": "", "hour": ""}]
        }, {
            "day": 30,
            "dayOfWeek": "poniedziałek",
            "classes": ["day-of-month-numeric__item", "event-listener"],
            "content": [{ "text": "","powiat": "", "hour": ""}]
        }, {
            "day": 1,
            "classes": ["text-grey", "day-of-month-numeric__item"],
            "content": [{ "text": "","powiat": "", "hour": ""}]
        }, {
            "day": 2,
            "classes": ["text-grey", "day-of-month-numeric__item"],
            "content": [{ "text": "","powiat": "", "hour": ""}]
        }, {
            "day": 3,
            "classes": ["text-grey", "day-of-month-numeric__item"],
            "content": [{ "text": "","powiat": "", "hour": ""}]
        }, {
            "day": 4,
            "classes": ["text-grey", "day-of-month-numeric__item"],
            "content": [{ "text": "","powiat": "", "hour": ""}]
        }, {
            "day": 5,
            "classes": ["text-grey", "day-of-month-numeric__item"],
            "content": [{ "text": "","powiat": "", "hour": ""}]
        }, {
            "day": 6,
            "classes": ["text-grey", "day-of-month-numeric__item"],
            "content": [{ "text": "","powiat": "", "hour": ""}]
        }
        ]
    },
        {"month": "październik",
        "data":  [
            {
                "day": 30,
                "classes": ["text-grey", "day-of-month-numeric__item"],
                "content": [{ "text": "","powiat": "", "hour": ""}]
            }, {
                "day": 1,
                "dayOfWeek": "wtorek",
                "classes": ["day-of-month-numeric__item", "event-listener"],
                "content": [{ "text": "","powiat": "", "hour": ""}]
            }, {
                "day": 2,
                "dayOfWeek": "środa",
                "classes": ["day-of-month-numeric__item", "event-listener"],
                "content": [{ "text": "","powiat": "", "hour": ""}]
            }, {
                "day": 3,
                "dayOfWeek": "czwartek",
                "classes": ["day-of-month-numeric__item", "event-listener"],
                "content": [{ "text": "","powiat": "", "hour": ""}]
            }, {
                "day": 4,
                "dayOfWeek": "piątek",
                "classes": ["day-of-month-numeric__item", "event-listener"],
                "content": [{ "text": "","powiat": "", "hour": ""}]
            }, {
                "day": 5,
                "dayOfWeek": "sobota",
                "classes": ["day-of-month-numeric__item", "event-listener"],
                "content": [{ "text": "","powiat": "", "hour": ""}]
            }, {
                "day": 6,
                "dayOfWeek": "niedziela",
                "classes": ["day-of-month-numeric__item", "event-listener"],
                "content": [{ "text": "","powiat": "", "hour": ""}]
            }, {
                "day": 7,
                "dayOfWeek": "poniedziałek",
                "classes": ["day-of-month-numeric__item", "event-listener"],
                "content": [{ "text": "","powiat": "", "hour": ""}]
            }, {
                "day": 8,
                "dayOfWeek": "wtorek",
                "classes": ["day-of-month-numeric__item", "event-listener"],
                "content": [{ "text": "","powiat": "", "hour": ""}]
            }, {
                "day": 9,
                "dayOfWeek": "środa",
                "classes": ["day-of-month-numeric__item", "event-listener"],
                "content": [{ "text": "","powiat": "", "hour": ""}]
            }, {
                "day": 10,
                "dayOfWeek": "czwartek",
                "classes": ["day-of-month-numeric__item", "event-listener"],
                "content": [{ "text": "","powiat": "", "hour": ""}]
            }, {
                "day": 11,
                "dayOfWeek": "piątek",
                "classes": ["day-of-month-numeric__item", "event-listener"],
                "content": [{ "text": "","powiat": "", "hour": ""}]
            }, {
                "day": 12,
                "dayOfWeek": "sobota",
                "classes": ["day-of-month-numeric__item", "event-listener"],
                "content": [{ "text": "","powiat": "", "hour": ""}]
            }, {
                "day": 13,
                "dayOfWeek": "niedziela",
                "classes": ["day-of-month-numeric__item", "event-listener"],
                "content": [{ "text": "","powiat": "", "hour": ""}]
            }, {
                "day": 14,
                "dayOfWeek": "poniedziałek",
                "classes": ["day-of-month-numeric__item", "event-listener"],
                "content": [{ "text": "","powiat": "", "hour": ""}]
            }, {
                "day": 15,
                "dayOfWeek": "wtorek",
                "classes": ["day-of-month-numeric__item", "event-listener"],
                "content": [{ "text": "","powiat": "", "hour": ""}]
            }, {
                "day": 16,
                "dayOfWeek": "środa",
                "classes": ["day-of-month-numeric__item", "event-listener"],
                "content": [{ "text": "","powiat": "", "hour": ""}]
            }, {
                "day": 17,
                "dayOfWeek": "czwartek",
                "classes": ["day-of-month-numeric__item", "event-listener"],
                "content": [{ "text": "","powiat": "", "hour": ""}]
            }, {
                "day": 18,
                "dayOfWeek": "piątek",
                "classes": ["day-of-month-numeric__item", "event-listener"],
                "content": [{ "text": "","powiat": "", "hour": ""}]
            }, {
                "day": 19,
                "dayOfWeek": "sobota",
                "classes": ["day-of-month-numeric__item", "event-listener"],
                "content": [{ "text": "","powiat": "", "hour": ""}]
            }, {
                "day": 20,
                "dayOfWeek": "niedziela",
                "classes": ["day-of-month-numeric__item", "event-listener"],
                "content": [{ "text": "","powiat": "", "hour": ""}]
            }, {
                "day": 21,
                "dayOfWeek": "poniedziałek",
                "classes": ["day-of-month-numeric__item", "event-listener"],
                "content": [{ "text": "","powiat": "", "hour": ""}]
            }, {
                "day": 22,
                "dayOfWeek": "wtorek",
                "classes": ["day-of-month-numeric__item", "event-listener"],
                "content": [{ "text": "","powiat": "", "hour": ""}]
            }, {
                "day": 23,
                "dayOfWeek": "środa",
                "classes": ["day-of-month-numeric__item", "event-listener"],
                "content": [{ "text": "","powiat": "", "hour": ""}]
            }, {
                "day": 24,
                "dayOfWeek": "czwartek",
                "classes": ["day-of-month-numeric__item", "event-listener"],
                "content": [{ "text": "","powiat": "", "hour": ""}]
            }, {
                "day": 25,
                "dayOfWeek": "piątek",
                "classes": ["day-of-month-numeric__item", "event-listener"],
                "content": [{ "text": "","powiat": "", "hour": ""}]
            }, {
                "day": 26,
                "dayOfWeek": "sobota",
                "classes": ["day-of-month-numeric__item", "event-listener"],
                "content": [{ "text": "","powiat": "", "hour": ""}]
            }, {
                "day": 27,
                "dayOfWeek": "niedziela",
                "classes": ["day-of-month-numeric__item", "event-listener"],
                "content": [{ "text": "","powiat": "", "hour": ""}]
            }, {
                "day": 28,
                "dayOfWeek": "poniedziałek",
                "classes": ["day-of-month-numeric__item", "event-listener"],
                "content": [{ "text": "","powiat": "", "hour": ""}]
            }, {
                "day": 29,
                "dayOfWeek": "wtorek",
                "classes": ["day-of-month-numeric__item", "event-listener"],
                "content": [{ "text": "","powiat": "", "hour": ""}]
            }, {
                "day": 30,
                "dayOfWeek": "środa",
                "classes": ["day-of-month-numeric__item", "event-listener"],
                "content": [{ "text": "","powiat": "", "hour": ""}]
            }, {
                "day": 31,
                "dayOfWeek": "czwartek",
                "classes": ["day-of-month-numeric__item", "event-listener"],
                "content": [{ "text": "","powiat": "", "hour": ""}]
            }, {
                "day": 1,
                "classes": ["text-grey", "day-of-month-numeric__item"],
                "content": [{ "text": "","powiat": "", "hour": ""}]
            }, {
                "day": 2,
                "classes": ["text-grey", "day-of-month-numeric__item"],
                "content": [{ "text": "","powiat": "", "hour": ""}]
            }, {
                "day": 3,
                "classes": ["text-grey", "day-of-month-numeric__item"],
                "content": [{ "text": "","powiat": "", "hour": ""}]
            }, {
                "day": 4,
                "classes": ["text-grey", "day-of-month-numeric__item"],
                "content": [{ "text": "","powiat": "", "hour": ""}]
            }, {
                "day": 5,
                "classes": ["text-grey", "day-of-month-numeric__item"],
                "content": [{ "text": "","powiat": "", "hour": ""}]
            }, {
                "day": 6,
                "classes": ["text-grey", "day-of-month-numeric__item"],
                "content": [{ "text": "","powiat": "", "hour": ""}]
            }, {
                "day": 7,
                "classes": ["text-grey", "day-of-month-numeric__item"],
                "content": [{ "text": "","powiat": "", "hour": ""}]
            }, {
                "day": 8,
                "classes": ["text-grey", "day-of-month-numeric__item"],
                "content": [{ "text": "","powiat": "", "hour": ""}]
            }, {
                "day": 9,
                "classes": ["text-grey", "day-of-month-numeric__item"],
                "content": [{ "text": "","powiat": "", "hour": ""}]
            }, {
                "day": 10,
                "classes": ["text-grey", "day-of-month-numeric__item"],
                "content": [{ "text": "","powiat": "", "hour": ""}]
            }
        ]}
    ],
    "mapa": [
        {"powiatClassifier": "map__powiat-zlotowski",
         "textContent": "głosuj na mnie w powiecie złotowskim"},
        {"powiatClassifier": "map__powiat-pilski",
            "textContent": "głosuj na mnie w powiecie pilskim"},
        {"powiatClassifier": "map__powiat-chodzieski",
            "textContent": "głosuj na mnie w powiecie chodzieskim"},
        {"powiatClassifier": "map__powiat-czarnkowsko-trzcianecki",
            "textContent": "głosuj na mnie w powiecie czarnkowsko-trzcianeckim"},
        {"powiatClassifier": "map__powiat-miedzychodzki",
            "textContent": "głosuj na mnie w powiecie międzychodzkim"},
        {"powiatClassifier": "map__powiat-szamotulski",
            "textContent": "głosuj na mnie w powiecie szamotulskim"},
        {"powiatClassifier": "map__powiat-obornicki",
            "textContent": "głosuj na mnie w powiecie obornickim"},
        {"powiatClassifier": "map__powiat-wagrowiecki",
            "textContent": "głosuj na mnie w powiecie wągrowieckim"},
        {"powiatClassifier": "map__powiat-nowotomyski",
            "textContent": "głosuj na mnie w powiecie nowotomyskim"},
        {"powiatClassifier": "map__powiat-wolsztynski",
            "textContent": "głosuj na mnie w powiecie wolsztyńskim"},
        {"powiatClassifier": "map__powiat-grodziski",
            "textContent": "głosuj na mnie w powiecie grodziskim"}

    ]

}

